{
	"info": {
		"_postman_id": "1cc0034b-1938-4ec2-9655-df803d413a9f",
		"name": "Swapi",
		"schema": "https://schema.getpostman.com/json/collection/v2.1.0/collection.json",
		"_exporter_id": "5302683"
	},
	"item": [
		{
			"name": "Get Planets",
			"request": {
				"method": "GET",
				"header": [],
				"url": {
					"raw": "{{base_url}}/planets",
					"host": [
						"{{base_url}}"
					],
					"path": [
						"planets"
					]
				}
			},
			"response": []
		},
		{
			"name": "Get People",
			"request": {
				"method": "GET",
				"header": [],
				"url": {
					"raw": "{{base_url}}/people",
					"host": [
						"{{base_url}}"
					],
					"path": [
						"people"
					]
				}
			},
			"response": []
		},
		{
			"name": "Get Vehicles",
			"request": {
				"method": "GET",
				"header": [],
				"url": {
					"raw": "{{base_url}}/vehicles",
					"host": [
						"{{base_url}}"
					],
					"path": [
						"vehicles"
					]
				}
			},
			"response": []
		},
		{
			"name": "Get Films",
			"request": {
				"method": "GET",
				"header": [],
				"url": {
					"raw": "{{base_url}}/films",
					"host": [
						"{{base_url}}"
					],
					"path": [
						"films"
					]
				}
			},
			"response": []
		},
		{
			"name": "Get Starships",
			"request": {
				"method": "GET",
				"header": [],
				"url": {
					"raw": "{{base_url}}/starships",
					"host": [
						"{{base_url}}"
					],
					"path": [
						"starships"
					]
				}
			},
			"response": []
		}
	],
	"event": [
		{
			"listen": "prerequest",
			"script": {
				"type": "text/javascript",
				"exec": [
					""
				]
			}
		},
		{
			"listen": "test",
			"script": {
				"type": "text/javascript",
				"exec": [
					""
				]
			}
		}
	],
	"variable": [
		{
			"key": "base_url",
			"value": "https://swapi.dev/api",
			"type": "string"
		}
	]
}